oct_analysis/__init__.py
oct_analysis/image_processing.py
oct_analysis-1.0.1.dist-info/licenses/LICENSE
oct_analysis-1.0.1.dist-info/METADATA
oct_analysis-1.0.1.dist-info/WHEEL
oct_analysis-1.0.1.dist-info/top_level.txt
oct_analysis-1.0.1.dist-info/RECORD
